dalle_generator/__init__.py
dalle_generator/api.py
dalle_generator/data.py
dalle_generator/webui.py
dalle_generator/templates/index.py
dalle_generator-25.3.5.dist-info/licenses/LICENSE
dalle_generator-25.3.5.dist-info/METADATA
dalle_generator-25.3.5.dist-info/WHEEL
dalle_generator-25.3.5.dist-info/top_level.txt
dalle_generator-25.3.5.dist-info/RECORD
