Metadata-Version: 2.4
Name: dalle-generator
Version: 25.3.5
Summary: A simple image generator that focuses on prompt adherence and aesthetics.
Author-email: ikmalsaid <ikmalsaid@gmail.com>
Project-URL: Homepage, https://github.com/ikmalsaid/dalle-generator
Project-URL: Issues, https://github.com/ikmalsaid/dalle-generator/issues
Keywords: dalle-generator,dalle_generator
Classifier: Programming Language :: Python :: 3
Classifier: Topic :: Scientific/Engineering :: Artificial Intelligence
Classifier: License :: OSI Approved :: GNU Affero General Public License v3
Classifier: Operating System :: OS Independent
Requires-Python: >=3.8
License-File: LICENSE
Requires-Dist: colorpaws
Requires-Dist: selenium
Requires-Dist: webdriver-manager
Requires-Dist: gradio==4.38.1
Requires-Dist: fastapi==0.112.4
Requires-Dist: pydantic==2.10.6
Requires-Dist: flask
Dynamic: license-file
